gopherfeed.py
setup.py
bin/gopherfeed
gopherfeed.egg-info/PKG-INFO
gopherfeed.egg-info/SOURCES.txt
gopherfeed.egg-info/dependency_links.txt
gopherfeed.egg-info/requires.txt
gopherfeed.egg-info/top_level.txt