Metadata-Version: 1.1
Name: gopherfeed
Version: 1.2
Summary: Convert RSS or Atom feeds to gophermap files
Home-page: https://github.com/lmaurits/gopherfeed
Author: Luke Maurits
Author-email: luke@maurits.id.au
License: BSD (3 clause)
Platform: UNKNOWN
Classifier: Programming Language :: Python
Classifier: License :: OSI Approved :: BSD License
Requires: feedparser
